Metadata-Version: 2.1
Name: configure-api-tests
Version: 0.0.1
Summary: Test suite design for the Configure API 
Author: Jacob Roscoe
Maintainer: Jacob Roscoe
License: Copyright (c) 2024 Wavelynx Technologies LLC
Project-URL: Source, https://gitlab.com/WaveLynxTech/configure-api-tests
Classifier: Development Status :: 4 - Beta
Classifier: Intended Audience :: Developers
Classifier: License :: OSI Approved :: MIT License
Classifier: Programming Language :: Python :: 3
Requires-Python: >=3.7
License-File: LICENSE.txt
